{
    "id": 1410,
    "name": "May the Dream Go On",
    "skill_name_asset": "-",
    "max_level": 8,
    "skill_effect_type": 11,
    "discharge_type": 1,
    "trigger_type": 4,
    "unit_skill_level_up_pattern_id": 4,
    "release_tag": null,
    "_encryption_release_id": null,
    "created_at": "2020-05-19 09:03:10",
    "updated_at": "2020-05-19 09:03:10",
    "unit_skill_levels": [
        {
            "id": 19892,
            "unit_skill_id": 1410,
            "skill_level": 1,
            "description": "For every 25 Combo, there's a 37% chance you'll gain 660 Score points.",
            "effect_range": 3,
            "effect_value": 660,
            "discharge_time": 0,
            "trigger_value": 25,
            "activation_rate": 37,
            "grant_exp": 1000,
            "release_tag": null,
            "_encryption_release_id": null,
            "created_at": "2020-05-19 09:03:07",
            "updated_at": "2020-05-19 09:03:07"
        },
        {
            "id": 19893,
            "unit_skill_id": 1410,
            "skill_level": 2,
            "description": "For every 25 Combo, there's a 41% chance you'll gain 1105 Score points.",
            "effect_range": 3,
            "effect_value": 1105,
            "discharge_time": 0,
            "trigger_value": 25,
            "activation_rate": 41,
            "grant_exp": 2000,
            "release_tag": null,
            "_encryption_release_id": null,
            "created_at": "2020-05-19 09:03:07",
            "updated_at": "2020-05-19 09:03:07"
        },
        {
            "id": 19894,
            "unit_skill_id": 1410,
            "skill_level": 3,
            "description": "For every 25 Combo, there's a 45% chance you'll gain 1550 Score points.",
            "effect_range": 3,
            "effect_value": 1550,
            "discharge_time": 0,
            "trigger_value": 25,
            "activation_rate": 45,
            "grant_exp": 4000,
            "release_tag": null,
            "_encryption_release_id": null,
            "created_at": "2020-05-19 09:03:07",
            "updated_at": "2020-05-19 09:03:07"
        },
        {
            "id": 19895,
            "unit_skill_id": 1410,
            "skill_level": 4,
            "description": "For every 25 Combo, there's a 49% chance you'll gain 1995 Score points.",
            "effect_range": 3,
            "effect_value": 1995,
            "discharge_time": 0,
            "trigger_value": 25,
            "activation_rate": 49,
            "grant_exp": 6000,
            "release_tag": null,
            "_encryption_release_id": null,
            "created_at": "2020-05-19 09:03:07",
            "updated_at": "2020-05-19 09:03:07"
        },
        {
            "id": 19896,
            "unit_skill_id": 1410,
            "skill_level": 5,
            "description": "For every 25 Combo, there's a 53% chance you'll gain 2440 Score points.",
            "effect_range": 3,
            "effect_value": 2440,
            "discharge_time": 0,
            "trigger_value": 25,
            "activation_rate": 53,
            "grant_exp": 9000,
            "release_tag": null,
            "_encryption_release_id": null,
            "created_at": "2020-05-19 09:03:07",
            "updated_at": "2020-05-19 09:03:07"
        },
        {
            "id": 19897,
            "unit_skill_id": 1410,
            "skill_level": 6,
            "description": "For every 25 Combo, there's a 57% chance you'll gain 2885 Score points.",
            "effect_range": 3,
            "effect_value": 2885,
            "discharge_time": 0,
            "trigger_value": 25,
            "activation_rate": 57,
            "grant_exp": 12000,
            "release_tag": null,
            "_encryption_release_id": null,
            "created_at": "2020-05-19 09:03:07",
            "updated_at": "2020-05-19 09:03:07"
        },
        {
            "id": 19898,
            "unit_skill_id": 1410,
            "skill_level": 7,
            "description": "For every 25 Combo, there's a 61% chance you'll gain 3330 Score points.",
            "effect_range": 3,
            "effect_value": 3330,
            "discharge_time": 0,
            "trigger_value": 25,
            "activation_rate": 61,
            "grant_exp": 15000,
            "release_tag": null,
            "_encryption_release_id": null,
            "created_at": "2020-05-19 09:03:07",
            "updated_at": "2020-05-19 09:03:07"
        },
        {
            "id": 19899,
            "unit_skill_id": 1410,
            "skill_level": 8,
            "description": "For every 25 Combo, there's a 65% chance you'll gain 3775 Score points.",
            "effect_range": 3,
            "effect_value": 3775,
            "discharge_time": 0,
            "trigger_value": 25,
            "activation_rate": 65,
            "grant_exp": 22000,
            "release_tag": null,
            "_encryption_release_id": null,
            "created_at": "2020-05-19 09:03:07",
            "updated_at": "2020-05-19 09:03:07"
        },
        {
            "id": 19900,
            "unit_skill_id": 1410,
            "skill_level": 9,
            "description": "-",
            "effect_range": 3,
            "effect_value": 4155,
            "discharge_time": 0,
            "trigger_value": 25,
            "activation_rate": 65,
            "grant_exp": 22000,
            "release_tag": null,
            "_encryption_release_id": null,
            "created_at": "2020-05-19 09:03:07",
            "updated_at": "2020-05-19 09:03:07"
        },
        {
            "id": 19901,
            "unit_skill_id": 1410,
            "skill_level": 10,
            "description": "-",
            "effect_range": 3,
            "effect_value": 4920,
            "discharge_time": 0,
            "trigger_value": 25,
            "activation_rate": 65,
            "grant_exp": 22000,
            "release_tag": null,
            "_encryption_release_id": null,
            "created_at": "2020-05-19 09:03:07",
            "updated_at": "2020-05-19 09:03:07"
        },
        {
            "id": 19902,
            "unit_skill_id": 1410,
            "skill_level": 11,
            "description": "-",
            "effect_range": 3,
            "effect_value": 6065,
            "discharge_time": 0,
            "trigger_value": 25,
            "activation_rate": 65,
            "grant_exp": 22000,
            "release_tag": null,
            "_encryption_release_id": null,
            "created_at": "2020-05-19 09:03:07",
            "updated_at": "2020-05-19 09:03:07"
        },
        {
            "id": 19903,
            "unit_skill_id": 1410,
            "skill_level": 12,
            "description": "-",
            "effect_range": 3,
            "effect_value": 7590,
            "discharge_time": 0,
            "trigger_value": 25,
            "activation_rate": 65,
            "grant_exp": 22000,
            "release_tag": null,
            "_encryption_release_id": null,
            "created_at": "2020-05-19 09:03:07",
            "updated_at": "2020-05-19 09:03:07"
        },
        {
            "id": 19904,
            "unit_skill_id": 1410,
            "skill_level": 13,
            "description": "-",
            "effect_range": 3,
            "effect_value": 8025,
            "discharge_time": 0,
            "trigger_value": 25,
            "activation_rate": 65,
            "grant_exp": 22000,
            "release_tag": null,
            "_encryption_release_id": null,
            "created_at": "2020-05-19 09:03:07",
            "updated_at": "2020-05-19 09:03:07"
        },
        {
            "id": 19905,
            "unit_skill_id": 1410,
            "skill_level": 14,
            "description": "-",
            "effect_range": 3,
            "effect_value": 8895,
            "discharge_time": 0,
            "trigger_value": 25,
            "activation_rate": 65,
            "grant_exp": 22000,
            "release_tag": null,
            "_encryption_release_id": null,
            "created_at": "2020-05-19 09:03:07",
            "updated_at": "2020-05-19 09:03:07"
        },
        {
            "id": 19906,
            "unit_skill_id": 1410,
            "skill_level": 15,
            "description": "-",
            "effect_range": 3,
            "effect_value": 10200,
            "discharge_time": 0,
            "trigger_value": 25,
            "activation_rate": 65,
            "grant_exp": 22000,
            "release_tag": null,
            "_encryption_release_id": null,
            "created_at": "2020-05-19 09:03:07",
            "updated_at": "2020-05-19 09:03:07"
        },
        {
            "id": 19907,
            "unit_skill_id": 1410,
            "skill_level": 16,
            "description": "-",
            "effect_range": 3,
            "effect_value": 11945,
            "discharge_time": 0,
            "trigger_value": 25,
            "activation_rate": 65,
            "grant_exp": 22000,
            "release_tag": null,
            "_encryption_release_id": null,
            "created_at": "2020-05-19 09:03:07",
            "updated_at": "2020-05-19 09:03:07"
        }
    ],
    "unit_skill_level_up_pattern": [
        {
            "id": 25,
            "unit_skill_level_up_pattern_id": 4,
            "skill_level": 1,
            "next_exp": 300,
            "created_at": "2016-11-17 02:40:09",
            "updated_at": "2016-12-08 18:01:33",
            "pivot": {
                "unit_skill_id": 1410,
                "unit_skill_level_up_pattern_id": 25
            }
        },
        {
            "id": 26,
            "unit_skill_level_up_pattern_id": 4,
            "skill_level": 2,
            "next_exp": 900,
            "created_at": "2016-11-17 02:40:09",
            "updated_at": "2016-12-08 18:01:33",
            "pivot": {
                "unit_skill_id": 1410,
                "unit_skill_level_up_pattern_id": 26
            }
        },
        {
            "id": 27,
            "unit_skill_level_up_pattern_id": 4,
            "skill_level": 3,
            "next_exp": 2400,
            "created_at": "2016-11-17 02:40:09",
            "updated_at": "2016-12-08 18:01:33",
            "pivot": {
                "unit_skill_id": 1410,
                "unit_skill_level_up_pattern_id": 27
            }
        },
        {
            "id": 28,
            "unit_skill_level_up_pattern_id": 4,
            "skill_level": 4,
            "next_exp": 5400,
            "created_at": "2016-11-17 02:40:09",
            "updated_at": "2016-12-08 18:01:33",
            "pivot": {
                "unit_skill_id": 1410,
                "unit_skill_level_up_pattern_id": 28
            }
        },
        {
            "id": 29,
            "unit_skill_level_up_pattern_id": 4,
            "skill_level": 5,
            "next_exp": 10400,
            "created_at": "2016-11-17 02:40:09",
            "updated_at": "2016-12-08 18:01:33",
            "pivot": {
                "unit_skill_id": 1410,
                "unit_skill_level_up_pattern_id": 29
            }
        },
        {
            "id": 30,
            "unit_skill_level_up_pattern_id": 4,
            "skill_level": 6,
            "next_exp": 17900,
            "created_at": "2016-11-17 02:40:09",
            "updated_at": "2016-12-08 18:01:33",
            "pivot": {
                "unit_skill_id": 1410,
                "unit_skill_level_up_pattern_id": 30
            }
        },
        {
            "id": 31,
            "unit_skill_level_up_pattern_id": 4,
            "skill_level": 7,
            "next_exp": 29900,
            "created_at": "2016-11-17 02:40:09",
            "updated_at": "2016-12-08 18:01:33",
            "pivot": {
                "unit_skill_id": 1410,
                "unit_skill_level_up_pattern_id": 31
            }
        },
        {
            "id": 32,
            "unit_skill_level_up_pattern_id": 4,
            "skill_level": 8,
            "next_exp": 0,
            "created_at": "2016-11-17 02:40:09",
            "updated_at": "2016-11-17 02:40:09",
            "pivot": {
                "unit_skill_id": 1410,
                "unit_skill_level_up_pattern_id": 32
            }
        }
    ]
}